abstract_nginx/__init__.py
abstract_nginx/file_utils/__init__.py
abstract_nginx/file_utils/conf_files.py
abstract_nginx/file_utils/file_utils.py
abstract_nginx/file_utils/request_files.py
abstract_nginx/file_utils/service_utils.py
abstract_nginx/file_utils/test.py
abstract_nginx/file_utils/imports/__init__.py
abstract_nginx/file_utils/imports/constants.py
abstract_nginx/file_utils/imports/imports.py
abstract_nginx-0.0.22.dist-info/METADATA
abstract_nginx-0.0.22.dist-info/WHEEL
abstract_nginx-0.0.22.dist-info/top_level.txt
abstract_nginx-0.0.22.dist-info/RECORD
